{"type": "directory", "dataset_id": "3e874376-b053-11e8-b9ac-0242ac130026", "dataset_version": "5be66b27ab5e033e9163caa94cec882bd4cee1d0", "children": [{"contentbytesize": 58, "dataset_id": "3e874376-b053-11e8-b9ac-0242ac130026", "dataset_version": "5be66b27ab5e033e9163caa94cec882bd4cee1d0", "metadata_sources": {"key_source_map": {}, "sources": [{"agent_email": "s.heunis@fz-juelich.de", "agent_name": "Stephan Heunis", "source_name": "metalad_core", "source_parameter": {}, "source_time": 1680125926.330397, "source_version": "1"}]}, "path": "derivatives/freesurfer/sub-CSI1/scripts/build-stamp.txt", "type": "file", "name": "build-stamp.txt"}, {"contentbytesize": 1, "dataset_id": "3e874376-b053-11e8-b9ac-0242ac130026", "dataset_version": "5be66b27ab5e033e9163caa94cec882bd4cee1d0", "metadata_sources": {"key_source_map": {}, "sources": [{"agent_email": "s.heunis@fz-juelich.de", "agent_name": "Stephan Heunis", "source_name": "metalad_core", "source_parameter": {}, "source_time": 1680125926.357213, "source_version": "1"}]}, "path": "derivatives/freesurfer/sub-CSI1/scripts/patchdir.txt", "type": "file", "name": "patchdir.txt"}, {"contentbytesize": 377, "dataset_id": "3e874376-b053-11e8-b9ac-0242ac130026", "dataset_version": "5be66b27ab5e033e9163caa94cec882bd4cee1d0", "metadata_sources": {"key_source_map": {}, "sources": [{"agent_email": "s.heunis@fz-juelich.de", "agent_name": "Stephan Heunis", "source_name": "metalad_core", "source_parameter": {}, "source_time": 1680125926.3621042, "source_version": "1"}]}, "path": "derivatives/freesurfer/sub-CSI1/scripts/pctsurfcon.log", "type": "file", "name": "pctsurfcon.log"}, {"contentbytesize": 58, "dataset_id": "3e874376-b053-11e8-b9ac-0242ac130026", "dataset_version": "5be66b27ab5e033e9163caa94cec882bd4cee1d0", "metadata_sources": {"key_source_map": {}, "sources": [{"agent_email": "s.heunis@fz-juelich.de", "agent_name": "Stephan Heunis", "source_name": "metalad_core", "source_parameter": {}, "source_time": 1680125926.352891, "source_version": "1"}]}, "path": "derivatives/freesurfer/sub-CSI1/scripts/lastcall.build-stamp.txt", "type": "file", "name": "lastcall.build-stamp.txt"}, {"contentbytesize": 208, "dataset_id": "3e874376-b053-11e8-b9ac-0242ac130026", "dataset_version": "5be66b27ab5e033e9163caa94cec882bd4cee1d0", "metadata_sources": {"key_source_map": {}, "sources": [{"agent_email": "s.heunis@fz-juelich.de", "agent_name": "Stephan Heunis", "source_name": "metalad_core", "source_parameter": {}, "source_time": 1680125926.546039, "source_version": "1"}]}, "path": "derivatives/freesurfer/sub-CSI1/scripts/ponscc.cut.log", "type": "file", "name": "ponscc.cut.log"}, {"contentbytesize": 377, "dataset_id": "3e874376-b053-11e8-b9ac-0242ac130026", "dataset_version": "5be66b27ab5e033e9163caa94cec882bd4cee1d0", "metadata_sources": {"key_source_map": {}, "sources": [{"agent_email": "s.heunis@fz-juelich.de", "agent_name": "Stephan Heunis", "source_name": "metalad_core", "source_parameter": {}, "source_time": 1680125926.542112, "source_version": "1"}]}, "path": "derivatives/freesurfer/sub-CSI1/scripts/pctsurfcon.log.old", "type": "file", "name": "pctsurfcon.log.old"}, {"contentbytesize": 995, "dataset_id": "3e874376-b053-11e8-b9ac-0242ac130026", "dataset_version": "5be66b27ab5e033e9163caa94cec882bd4cee1d0", "metadata_sources": {"key_source_map": {}, "sources": [{"agent_email": "s.heunis@fz-juelich.de", "agent_name": "Stephan Heunis", "source_name": "metalad_core", "source_parameter": {}, "source_time": 1680125926.590823, "source_version": "1"}]}, "path": "derivatives/freesurfer/sub-CSI1/scripts/recon-all-status-rh.log", "type": "file", "name": "recon-all-status-rh.log"}, {"contentbytesize": 4110, "dataset_id": "3e874376-b053-11e8-b9ac-0242ac130026", "dataset_version": "5be66b27ab5e033e9163caa94cec882bd4cee1d0", "metadata_sources": {"key_source_map": {}, "sources": [{"agent_email": "s.heunis@fz-juelich.de", "agent_name": "Stephan Heunis", "source_name": "metalad_core", "source_parameter": {}, "source_time": 1680125926.576493, "source_version": "1"}]}, "path": "derivatives/freesurfer/sub-CSI1/scripts/recon-all-rh.cmd", "type": "file", "name": "recon-all-rh.cmd"}, {"contentbytesize": 80972, "dataset_id": "3e874376-b053-11e8-b9ac-0242ac130026", "dataset_version": "5be66b27ab5e033e9163caa94cec882bd4cee1d0", "metadata_sources": {"key_source_map": {}, "sources": [{"agent_email": "s.heunis@fz-juelich.de", "agent_name": "Stephan Heunis", "source_name": "metalad_core", "source_parameter": {}, "source_time": 1680125926.592132, "source_version": "1"}]}, "path": "derivatives/freesurfer/sub-CSI1/scripts/recon-all-rh.log", "type": "file", "name": "recon-all-rh.log"}, {"contentbytesize": 78895, "dataset_id": "3e874376-b053-11e8-b9ac-0242ac130026", "dataset_version": "5be66b27ab5e033e9163caa94cec882bd4cee1d0", "metadata_sources": {"key_source_map": {}, "sources": [{"agent_email": "s.heunis@fz-juelich.de", "agent_name": "Stephan Heunis", "source_name": "metalad_core", "source_parameter": {}, "source_time": 1680125926.577455, "source_version": "1"}]}, "path": "derivatives/freesurfer/sub-CSI1/scripts/recon-all-lh.log", "type": "file", "name": "recon-all-lh.log"}, {"contentbytesize": 4110, "dataset_id": "3e874376-b053-11e8-b9ac-0242ac130026", "dataset_version": "5be66b27ab5e033e9163caa94cec882bd4cee1d0", "metadata_sources": {"key_source_map": {}, "sources": [{"agent_email": "s.heunis@fz-juelich.de", "agent_name": "Stephan Heunis", "source_name": "metalad_core", "source_parameter": {}, "source_time": 1680125926.573496, "source_version": "1"}]}, "path": "derivatives/freesurfer/sub-CSI1/scripts/recon-all-lh.cmd", "type": "file", "name": "recon-all-lh.cmd"}, {"contentbytesize": 995, "dataset_id": "3e874376-b053-11e8-b9ac-0242ac130026", "dataset_version": "5be66b27ab5e033e9163caa94cec882bd4cee1d0", "metadata_sources": {"key_source_map": {}, "sources": [{"agent_email": "s.heunis@fz-juelich.de", "agent_name": "Stephan Heunis", "source_name": "metalad_core", "source_parameter": {}, "source_time": 1680125926.5997639, "source_version": "1"}]}, "path": "derivatives/freesurfer/sub-CSI1/scripts/recon-all-status-lh.log", "type": "file", "name": "recon-all-status-lh.log"}, {"contentbytesize": 3205, "dataset_id": "3e874376-b053-11e8-b9ac-0242ac130026", "dataset_version": "5be66b27ab5e033e9163caa94cec882bd4cee1d0", "metadata_sources": {"key_source_map": {}, "sources": [{"agent_email": "s.heunis@fz-juelich.de", "agent_name": "Stephan Heunis", "source_name": "metalad_core", "source_parameter": {}, "source_time": 1680125926.783617, "source_version": "1"}]}, "path": "derivatives/freesurfer/sub-CSI1/scripts/recon-all-status.log", "type": "file", "name": "recon-all-status.log"}, {"contentbytesize": 27879, "dataset_id": "3e874376-b053-11e8-b9ac-0242ac130026", "dataset_version": "5be66b27ab5e033e9163caa94cec882bd4cee1d0", "metadata_sources": {"key_source_map": {}, "sources": [{"agent_email": "s.heunis@fz-juelich.de", "agent_name": "Stephan Heunis", "source_name": "metalad_core", "source_parameter": {}, "source_time": 1680125926.786056, "source_version": "1"}]}, "path": "derivatives/freesurfer/sub-CSI1/scripts/recon-all.cmd", "type": "file", "name": "recon-all.cmd"}, {"contentbytesize": 720, "dataset_id": "3e874376-b053-11e8-b9ac-0242ac130026", "dataset_version": "5be66b27ab5e033e9163caa94cec882bd4cee1d0", "metadata_sources": {"key_source_map": {}, "sources": [{"agent_email": "s.heunis@fz-juelich.de", "agent_name": "Stephan Heunis", "source_name": "metalad_core", "source_parameter": {}, "source_time": 1680125926.794514, "source_version": "1"}]}, "path": "derivatives/freesurfer/sub-CSI1/scripts/recon-all.done", "type": "file", "name": "recon-all.done"}, {"contentbytesize": 2450, "dataset_id": "3e874376-b053-11e8-b9ac-0242ac130026", "dataset_version": "5be66b27ab5e033e9163caa94cec882bd4cee1d0", "metadata_sources": {"key_source_map": {}, "sources": [{"agent_email": "s.heunis@fz-juelich.de", "agent_name": "Stephan Heunis", "source_name": "metalad_core", "source_parameter": {}, "source_time": 1680125926.803838, "source_version": "1"}]}, "path": "derivatives/freesurfer/sub-CSI1/scripts/recon-all.env", "type": "file", "name": "recon-all.env"}, {"contentbytesize": 462509, "dataset_id": "3e874376-b053-11e8-b9ac-0242ac130026", "dataset_version": "5be66b27ab5e033e9163caa94cec882bd4cee1d0", "metadata_sources": {"key_source_map": {}, "sources": [{"agent_email": "s.heunis@fz-juelich.de", "agent_name": "Stephan Heunis", "source_name": "metalad_core", "source_parameter": {}, "source_time": 1680125926.83305, "source_version": "1"}]}, "path": "derivatives/freesurfer/sub-CSI1/scripts/recon-all.log", "type": "file", "name": "recon-all.log"}, {"contentbytesize": 2404, "dataset_id": "3e874376-b053-11e8-b9ac-0242ac130026", "dataset_version": "5be66b27ab5e033e9163caa94cec882bd4cee1d0", "metadata_sources": {"key_source_map": {}, "sources": [{"agent_email": "s.heunis@fz-juelich.de", "agent_name": "Stephan Heunis", "source_name": "metalad_core", "source_parameter": {}, "source_time": 1680125926.814942, "source_version": "1"}]}, "path": "derivatives/freesurfer/sub-CSI1/scripts/recon-all.env.bak", "type": "file", "name": "recon-all.env.bak"}, {"contentbytesize": 327555, "dataset_id": "3e874376-b053-11e8-b9ac-0242ac130026", "dataset_version": "5be66b27ab5e033e9163caa94cec882bd4cee1d0", "metadata_sources": {"key_source_map": {}, "sources": [{"agent_email": "s.heunis@fz-juelich.de", "agent_name": "Stephan Heunis", "source_name": "metalad_core", "source_parameter": {}, "source_time": 1680125926.821059, "source_version": "1"}]}, "path": "derivatives/freesurfer/sub-CSI1/scripts/recon-all.local-copy", "type": "file", "name": "recon-all.local-copy"}], "path": "derivatives/freesurfer/sub-CSI1/scripts", "name": "scripts"}